[
    {
        "x": 35,
        "y": 85,
        "label": "Crab",
        "type": "seafood"
    },
    {
        "x": 17,
        "y": 87,
        "label": "Crab",
        "type": "seafood"
    },
    {
        "x": 83,
        "y": 85,
        "label": "Crab",
        "type": "seafood"
    },
    {
        "x": 30,
        "y": 45,
        "label": "Cranberry",
        "type": "fruit"
    },
    {
        "x": 20,
        "y": 51,
        "label": "Cranberry",
        "type": "fruit"
    },
    {
        "x": 15,
        "y": 55,
        "label": "Spinach",
        "type": "vegetable"
    },
    {
        "x": 18,
        "y": 53,
        "label": "Elderberry",
        "type": "fruit"
    },
    {
        "x": 33,
        "y": 53,
        "label": "Watercress",
        "type": "vegetable"
    },
    {
        "x": 31.5,
        "y": 46.5,
        "label": "Lettuce",
        "type": "vegetable"
    },
    {
        "x": 21,
        "y": 65,
        "label": "Mushroom",
        "type": "vegetable"
    },
    {
        "x": 22,
        "y": 69,
        "label": "Wild Carrot",
        "type": "vegetable"
    },
    {
        "x": 22,
        "y": 79,
        "label": "Red Apple",
        "type": "fruit"
    },
    {
        "x": 58,
        "y": 76,
        "label": "Milk & Wheat",
        "type": "store"
    },
    {
        "x": 66,
        "y": 71,
        "label": "Nabiha's Berries",
        "type": "store"
    },
    {
        "x": 64,
        "y": 72,
        "label": "Greenstalk",
        "type": "store"
    },
    {
        "x": 61.5,
        "y": 72,
        "label": "Chop",
        "type": "store"
    },
    {
        "x": 60,
        "y": 70,
        "label": "Town Hall",
        "type": "store"
    },
    {
        "x": 67,
        "y": 78.5,
        "label": "Bits & Pieces",
        "type": "store"
    },
    {
        "x": 73,
        "y": 75,
        "label": "Eight Eleven",
        "type": "store"
    },
    {
        "x": 69,
        "y": 68,
        "label": "Valentina's Infirmary",
        "type": "store"
    },
    {
        "x": 61.5,
        "y": 83.5,
        "label": "Fish King",
        "type": "store"
    },
    {
        "x": 63,
        "y": 76,
        "label": "La Galerie",
        "type": "store"
    },
    {
        "x": 61,
        "y": 78,
        "label": "Hotel Rose",
        "type": "store"
    },
    {
        "x": 55,
        "y": 76,
        "label": "Bibi Apartments",
        "type": "store"
    },
    {
        "x": 45,
        "y": 82,
        "label": "Asparagus",
        "type": "vegetable"
    }, 
    {
        "x": 40,
        "y": 68.5,
        "label": "Chili",
        "type": "fruit"
    },
    {
        "x": 42,
        "y": 69,
        "label": "Raspberry",
        "type": "fruit"
    },
    {
        "x": 42.5,
        "y": 70,
        "label": "Red Apple",
        "type": "fruit"
    },
    {
        "x": 36,
        "y": 69,
        "label": "Sugarcane",
        "type": "grass"
    },
    {
        "x": 37,
        "y": 60,
        "label": "Elderberry",
        "type": "fruit"
    },
    {
        "x": 37,
        "y": 62,
        "label": "Chili",
        "type": "fruit"
    },
    {
        "x": 33.5,
        "y": 61,
        "label": "Wild Carrot",
        "type": "vegetable"
    },
    {
        "x": 32,
        "y": 61,
        "label": "Elderberry",
        "type": "fruit"
    },
    {
        "x": 28,
        "y": 59,
        "label": "Cranberry",
        "type": "fruit"
    },
    {
        "x": 28,
        "y": 55,
        "label": "Cranberry",
        "type": "fruit"
    },
    {
        "x": 28,
        "y": 52,
        "label": "Watercress",
        "type": "vegetable"
    },
    {
        "x": 26.2,
        "y": 49,
        "label": "Asparagus",
        "type": "vegetable"
    },
    {
        "x": 26,
        "y": 47,
        "label": "Cranberry",
        "type": "fruit"
    },
    {
        "x": 29,
        "y": 47.5,
        "label": "Wild Rice",
        "type": "grain"
    },
    {
        "x": 35,
        "y": 46.5,
        "label": "Chili",
        "type": "fruit"
    },
    {
        "x": 38,
        "y": 45,
        "label": "Elderberry",
        "type": "fruit"
    },
    {
        "x": 39,
        "y": 43,
        "label": "Asparagus",
        "type": "vegetable"
    },
    {
        "x": 39.5,
        "y": 43.25,
        "label": "Wild Rice",
        "type": "grain"
    },
    {
        "x": 41.5,
        "y": 43,
        "label": "Mushroom",
        "type": "vegetable"
    },
    {
        "x": 40,
        "y": 50,
        "label": "Wild Rice",
        "type": "grain"
    },
    {
        "x": 40,
        "y": 52,
        "label": "Watercress",
        "type": "vegetable"
    },
    {
        "x": 43.5,
        "y": 52.5,
        "label": "Elderberry",
        "type": "fruit"
    },
    {
        "x": 45,
        "y": 54.5,
        "label": "Elderberry",
        "type": "fruit"
    },
    {
        "x": 47,
        "y": 56.5,
        "label": "Raspberry",
        "type": "fruit"
    },
    {
        "x": 44.5,
        "y": 60,
        "label": "Chili",
        "type": "fruit"
    },
    {
        "x": 48,
        "y": 59,
        "label": "Raspberry",
        "type": "fruit"
    },
    {
        "x": 73,
        "y": 70,
        "label": "Red Apple",
        "type": "fruit"
    },
    {
        "x": 70,
        "y": 73,
        "label": "Raspberry",
        "type": "fruit"
    },
    {
        "x": 72,
        "y": 69.5,
        "label": "Asparagus",
        "type": "vegetable"
    },
    {
        "x": 79,
        "y": 79.5,
        "label": "Mushroom",
        "type": "vegetable"
    },
    {
        "x": 85,
        "y": 83,
        "label": "Clam",
        "type": "seafood"
    },
    {
        "x": 86,
        "y": 79,
        "label": "Clam",
        "type": "seafood"
    },
    {
        "x": 87,
        "y": 70,
        "label": "Wild Carrot",
        "type": "vegetable"
    },
    {
        "x": 84,
        "y": 65,
        "label": "Elderberry",
        "type": "fruit"
    },
    {
        "x": 86,
        "y": 63,
        "label": "Lettuce",
        "type": "vegetable"
    },
    {
        "x": 86,
        "y": 67,
        "label": "Unknown",
        "type": "fruit"
    },
    {
        "x": 78,
        "y": 58,
        "label": "Mint Leaf",
        "type": "herb"
    },
    {
        "x": 77.5,
        "y": 61,
        "label": "Spinach",
        "type": "vegetable"
    },
    {
        "x": 78,
        "y": 73,
        "label": "Mint Leaf",
        "type": "herb"
    },
    {
        "x": 82,
        "y": 69,
        "label": "Mint Leaf",
        "type": "herb"
    },
    {
        "x": 71.5,
        "y": 56,
        "label": "Sorghum",
        "type": "grain"
    },
    {
        "x": 72.5,
        "y": 53,
        "label": "Sorghum",
        "type": "grain"
    },
    {
        "x": 66.5,
        "y": 52.5,
        "label": "Sorghum",
        "type": "grain"
    },
    {
        "x": 63.5,
        "y": 53,
        "label": "Tea Leaves",
        "type": "herb"
    }
    

]